demix_lib/__init__.py
demix_lib/demix_colormaps.py
demix_lib/demix_lib_configuration.py
demix_lib/demix_pixels.py
demix_lib/demix_score.py
demix_lib/demix_url_handler.py
demix_lib/demix_utility.py
demix_lib-1.13.dist-info/LICENCE.txt
demix_lib-1.13.dist-info/METADATA
demix_lib-1.13.dist-info/WHEEL
demix_lib-1.13.dist-info/top_level.txt
demix_lib-1.13.dist-info/RECORD
