Metadata-Version: 2.1
Name: demix-lib
Version: 1.13
Summary: version 1.13 of the DEMIX library
Home-page: https://github.com/AlexisMARTICOMTE/demix_lib.git
Author: visioterra
Author-email: info@visioterra.fr
License: mit
Platform: UNKNOWN
